edisgo/__init__.py
edisgo/edisgo.py
edisgo/config/config_db_tables_default.cfg
edisgo/config/config_grid_default.cfg
edisgo/config/config_grid_expansion_default.cfg
edisgo/config/config_opf_julia_default.cfg
edisgo/config/config_system.cfg
edisgo/config/config_timeseries_default.cfg
edisgo/equipment/equipment-parameters_LV_cables.csv
edisgo/equipment/equipment-parameters_LV_transformers.csv
edisgo/equipment/equipment-parameters_MV_cables.csv
edisgo/equipment/equipment-parameters_MV_overhead_lines.csv
edisgo/equipment/equipment-parameters_MV_transformers.csv
edisgo/flex_opt/__init__.py
edisgo/flex_opt/charging_strategies.py
edisgo/flex_opt/check_tech_constraints.py
edisgo/flex_opt/costs.py
edisgo/flex_opt/curtailment.py
edisgo/flex_opt/exceptions.py
edisgo/flex_opt/heat_pump_operation.py
edisgo/flex_opt/q_control.py
edisgo/flex_opt/reinforce_grid.py
edisgo/flex_opt/reinforce_measures.py
edisgo/flex_opt/storage_positioning.py
edisgo/io/__init__.py
edisgo/io/ding0_import.py
edisgo/io/electromobility_import.py
edisgo/io/generators_import.py
edisgo/io/heat_pump_import.py
edisgo/io/pypsa_io.py
edisgo/io/timeseries_import.py
edisgo/network/__init__.py
edisgo/network/components.py
edisgo/network/electromobility.py
edisgo/network/grids.py
edisgo/network/heat.py
edisgo/network/results.py
edisgo/network/timeseries.py
edisgo/network/topology.py
edisgo/opf/__init__.py
edisgo/opf/run_mp_opf.py
edisgo/opf/run_opf_test.py
edisgo/opf/test_path.py
edisgo/opf/timeseries_reduction.py
edisgo/opf/edisgo_scenario_data/__init__.py
edisgo/opf/opf_solutions/__init__.py
edisgo/opf/results/__init__.py
edisgo/opf/results/opf_expand_network.py
edisgo/opf/results/opf_result_class.py
edisgo/opf/util/__init__.py
edisgo/opf/util/plot_solutions.py
edisgo/opf/util/scenario_settings.py
edisgo/tools/__init__.py
edisgo/tools/config.py
edisgo/tools/geo.py
edisgo/tools/geopandas_helper.py
edisgo/tools/logger.py
edisgo/tools/networkx_helper.py
edisgo/tools/plots.py
edisgo/tools/powermodels_io.py
eDisGo-0.2.1.dist-info/LICENSE
eDisGo-0.2.1.dist-info/METADATA
eDisGo-0.2.1.dist-info/WHEEL
eDisGo-0.2.1.dist-info/top_level.txt
eDisGo-0.2.1.dist-info/RECORD
