Metadata-Version: 2.1
Name: eDisGo
Version: 0.2.1
Summary: A python package for distribution network analysis and optimization
Home-page: https://github.com/openego/eDisGo
Author: birgits, AnyaHe, khelfen, gplssm, nesnoj, jaappedersen, Elias, boltbeard, mltja
Author-email: anya.heider@rl-institut.de
License: GNU Affero General Public License v3.0
License-File: LICENSE
Requires-Dist: demandlib
Requires-Dist: networkx (>=2.5.0)
Requires-Dist: geopy (>=2.0.0)
Requires-Dist: pandas (>=1.2.0)
Requires-Dist: geopandas (>=0.12.0)
Requires-Dist: pyproj (>=3.0.0)
Requires-Dist: shapely (>=1.7.0)
Requires-Dist: pypsa (<=0.20.1,>=0.17.0)
Requires-Dist: pyomo (<=6.4.2)
Requires-Dist: multiprocess
Requires-Dist: workalendar
Requires-Dist: sqlalchemy (<1.4.0)
Requires-Dist: geoalchemy2 (<0.7.0)
Requires-Dist: egoio (>=0.4.7)
Requires-Dist: matplotlib (>=3.3.0)
Requires-Dist: pypower
Requires-Dist: scikit-learn
Requires-Dist: pydot
Requires-Dist: pygeos
Requires-Dist: beautifulsoup4
Requires-Dist: contextily
Requires-Dist: descartes
Requires-Dist: jupyterlab
Requires-Dist: plotly
Requires-Dist: dash
Requires-Dist: jupyter-dash
Provides-Extra: dev
Requires-Dist: pytest ; extra == 'dev'
Requires-Dist: pytest-notebook ; extra == 'dev'
Requires-Dist: sphinx (<5.1.0,>=4.3.0) ; extra == 'dev'
Requires-Dist: sphinx-rtd-theme (>=0.5.2) ; extra == 'dev'
Requires-Dist: sphinx-autodoc-typehints ; extra == 'dev'
Requires-Dist: sphinx-autoapi ; extra == 'dev'
Requires-Dist: pre-commit ; extra == 'dev'
Requires-Dist: black ; extra == 'dev'
Requires-Dist: isort ; extra == 'dev'
Requires-Dist: pyupgrade ; extra == 'dev'
Requires-Dist: flake8 ; extra == 'dev'
Requires-Dist: pylint ; extra == 'dev'
